{
    "skills": {
        "front": [
            {
                "name": "Javascript",
                "rating": 4
            },
            {
                "name": "HTML",
                "rating": 3
            },
            {
                "name": "React",
                "rating": 3
            },
            {
                "name": "Angular",
                "rating": 2.5
            }
        ],
        "mobile": [
            {
                "name": "React Native",
                "rating": 2.5
            },
            {
                "name": "Ionic",
                "rating": 3
            },
            {
                "name": "Android",
                "rating": 2
            }
        ],
        "back": [
            {
                "name": "Node.js",
                "rating": 4
            },
            {
                "name": "SQL",
                "rating": 3.5
            },
            {
                "name": "NOSQL",
                "rating": 3
            }
        ]
    },
    "repositories": [
        {
            "name": "agendaConsulta",
            "description": "Aplicação simplificada, com objetivo de atender necessidades de consultórios médicos em controlar agenda de consultas. Nele é possível cadastrar médicos e consultas, com controle de intervalo de tempo entre as consultas. O foco do projeto foi a construção do front-end utilizando React, por tanto, não houve a construção de um back-end complexo, mas para lógica de armazenamento e consultado de dados, a biblioteca Json Server foi utilizada para gerar uma API REST.",
            "html_url": "https://github.com/welingtonfidelis/agendaConsulta",
            "image_url": [
                "https://welingtonfidelisportfolio.s3-sa-east-1.amazonaws.com/repositories/AgendaConsulta.png",
                "https://welingtonfidelisportfolio.s3-sa-east-1.amazonaws.com/repositories/agendaConsulta2.png",
                "https://welingtonfidelisportfolio.s3-sa-east-1.amazonaws.com/repositories/agendaConsulta3.png"
            ]
        },
        {
            "name": "agendaFacil",
            "description": "Refatoração da aplicação agendaConsulta, este projeto teve melhorias visuais, estruturais e construção de uma API REST com Node.js e banco de dados SQLite.",
            "html_url": "https://github.com/welingtonfidelis/agendaFacil",
            "image_url": [
                "https://welingtonfidelisportfolio.s3-sa-east-1.amazonaws.com/repositories/agendaFacil2.png",
                "https://welingtonfidelisportfolio.s3-sa-east-1.amazonaws.com/repositories/agendaFacil3.png",
                "https://welingtonfidelisportfolio.s3-sa-east-1.amazonaws.com/repositories/agendaFacil4.png",
                "https://welingtonfidelisportfolio.s3-sa-east-1.amazonaws.com/repositories/agendaFacil5.png",
                "https://welingtonfidelisportfolio.s3-sa-east-1.amazonaws.com/repositories/agendaFacil6.png",
                "https://welingtonfidelisportfolio.s3-sa-east-1.amazonaws.com/repositories/agendaFacil7.png",
                "https://welingtonfidelisportfolio.s3-sa-east-1.amazonaws.com/repositories/agendaFacil8.png"
            ]
        },
        {
            "name": "Alcool",
            "description": "Aplicação construida em PHP, HTML, Jquery e MySQL com objetivo de cadastro e oferta de produtos (atualmente, apenas álcool em gel). A aplicação é dividida em três perfis: ADMINISTRADOR, capaz de aprovar/recusar cadastro de fornecedores e produtos, FORNECEDOR, capaz de cadastrar novos produtos e aprovar/recusar pedidos e CLIENTES, que podem se cadastrar e efetuar pedidos de produtos disponíveis.",
            "html_url": "https://github.com/welingtonfidelis/Alcool",
            "image_url": [
                "https://images.unsplash.com/photo-1581287053822-fd7bf4f4bfec?ixlib=rb-1.2.1&ixid=eyJhcHBfaWQiOjEyMDd9&auto=format&fit=crop&w=900&q=80"
            ]
        },
        {
            "name": "api-busca-vagaomnibees",
            "description": "Este projeto construído através de Node.js, tem objetivo de trabalhar como um Crawler, buscando informações sobre quartos de hotéis em respostas de páginas web, mais específicamente, páginas retornadas por buscas no hotel Le Canton (https://lecanton.com.br/).",
            "html_url": "https://github.com/welingtonfidelis/api-busca-vagaomnibees",
            "image_url": [
                "https://welingtonfidelisportfolio.s3-sa-east-1.amazonaws.com/repositories/api-busca-vagaomnibees.png"
            ]
        },
        {
            "name": "ClimaCidade-api/web",
            "description": "API REST em NodeJs e MongoDB juntamente com uma página web em React (ClimaCidade-web). A aplicação ClimaCidade fornece ao usuário a possibilidade de buscar informações sobre o clima de cidades através de uma busca na API OpenWeatherMap. Também é possível através aplicação conferir as 5 cidades mais buscadas e o histórico de buscas, ambos atualizados em tempo real com uso de socket.",
            "html_url": "https://github.com/welingtonfidelis/ClimaCidade-api",
            "image_url": [
                "https://welingtonfidelisportfolio.s3-sa-east-1.amazonaws.com/repositories/Clima_Cidade.png"
            ],
            "deploy": "https://welingtonfidelis.github.io/ClimaCidade-web"
        },
        {
            "name": "compreAqui",
            "description": "Projeto com objetivo de funcionar como um mini OLX, com cadastro cliente e de comércio e seus produtos. A parte web (voltada ao comerciante) foi construída com React, o aplicativo construído em React Native (voltado ao cliente) e o back-end em Node.js, Graphql e banco Postgres.",
            "html_url": "https://github.com/welingtonfidelis/compreAqui",
            "image_url": [
                "https://welingtonfidelisportfolio.s3-sa-east-1.amazonaws.com/repositories/compre_aqui_1.png",
                "https://welingtonfidelisportfolio.s3-sa-east-1.amazonaws.com/repositories/compre_aqui_2.png",
                "https://welingtonfidelisportfolio.s3-sa-east-1.amazonaws.com/repositories/compre_aqui_3.png",
                "https://welingtonfidelisportfolio.s3-sa-east-1.amazonaws.com/repositories/compre_aqui_4.png",
                "https://welingtonfidelisportfolio.s3-sa-east-1.amazonaws.com/repositories/compre_aqui_5.png",
                "https://welingtonfidelisportfolio.s3-sa-east-1.amazonaws.com/repositories/compre_aqui_6.png",
                "https://welingtonfidelisportfolio.s3-sa-east-1.amazonaws.com/repositories/compre_aqui_7.png",
                "https://welingtonfidelisportfolio.s3-sa-east-1.amazonaws.com/repositories/compre_aqui_8.png",
                "https://welingtonfidelisportfolio.s3-sa-east-1.amazonaws.com/repositories/compre_aqui_9.png",
                "https://welingtonfidelisportfolio.s3-sa-east-1.amazonaws.com/repositories/compre_aqui_10.png",
                "https://welingtonfidelisportfolio.s3-sa-east-1.amazonaws.com/repositories/compre_aqui_11.png",
                "https://welingtonfidelisportfolio.s3-sa-east-1.amazonaws.com/repositories/compre_aqui_12.png",
                "https://welingtonfidelisportfolio.s3-sa-east-1.amazonaws.com/repositories/compre_aqui_19.png",
                "https://welingtonfidelisportfolio.s3-sa-east-1.amazonaws.com/repositories/compre_aqui_13.png",
                "https://welingtonfidelisportfolio.s3-sa-east-1.amazonaws.com/repositories/compre_aqui_14.png",
                "https://welingtonfidelisportfolio.s3-sa-east-1.amazonaws.com/repositories/compre_aqui_15.png",
                "https://welingtonfidelisportfolio.s3-sa-east-1.amazonaws.com/repositories/compre_aqui_16.png",
                "https://welingtonfidelisportfolio.s3-sa-east-1.amazonaws.com/repositories/compre_aqui_17.png",
                "https://welingtonfidelisportfolio.s3-sa-east-1.amazonaws.com/repositories/compre_aqui_18.png"
            ]
        },
        {
            "name": "control-payment-api/front",
            "description": "Aplicação que visa atender necessidades de ONGs no de controle de caixa (entrada e saída), controle de contribuintes e doações mensais. Front-end construído em React e back-end em Node.js e banco de dados Postgres.",
            "html_url": "https://github.com/welingtonfidelis/control-payment-api",
            "image_url": [
                "https://welingtonfidelisportfolio.s3-sa-east-1.amazonaws.com/repositories/COntrol_payment.png",
                "https://welingtonfidelisportfolio.s3-sa-east-1.amazonaws.com/repositories/COntrol_payment2.png",
                "https://welingtonfidelisportfolio.s3-sa-east-1.amazonaws.com/repositories/COntrol_payment3.png",
                "https://welingtonfidelisportfolio.s3-sa-east-1.amazonaws.com/repositories/COntrol_payment4.png",
                "https://welingtonfidelisportfolio.s3-sa-east-1.amazonaws.com/repositories/COntrol_payment5.png",
                "https://welingtonfidelisportfolio.s3-sa-east-1.amazonaws.com/repositories/COntrol_payment6.png",
                "https://welingtonfidelisportfolio.s3-sa-east-1.amazonaws.com/repositories/COntrol_payment7.png",
                "https://welingtonfidelisportfolio.s3-sa-east-1.amazonaws.com/repositories/COntrol_payment8.png",
                "https://welingtonfidelisportfolio.s3-sa-east-1.amazonaws.com/repositories/COntrol_payment9.png",
                "https://welingtonfidelisportfolio.s3-sa-east-1.amazonaws.com/repositories/COntrol_payment10.png",
                "https://welingtonfidelisportfolio.s3-sa-east-1.amazonaws.com/repositories/COntrol_payment11.png"
            ],
            "deploy": "https://welingtonfidelis.github.io/control-payment-front"
        },
        {
            "name": "CRUD-Question-GraphQL",
            "description": "Aplicação construída com Nodejs, React, GraphQL (Relay no React) e MongoDB. O objetivo foi criar um CRUD básico de perguntas multipla escolha.",
            "html_url": "https://github.com/welingtonfidelis/CRUD-Question-GraphQL/CRUD-Question-GraphQL",
            "image_url": [
                "https://welingtonfidelisportfolio.s3-sa-east-1.amazonaws.com/repositories/CRUD_Graphql.png"
            ]
        },
        {
            "name": "docker-compose-test",
            "description": "Projeto teste para aplicação de docker-compose na criação de containers de bancos de dados, documentação através do mkdocs e um servidor em nodejs.",
            "html_url": "https://github.com/welingtonfidelis/docker-compose-test",
            "image_url": [
                "https://welingtonfidelisportfolio.s3-sa-east-1.amazonaws.com/repositories/docker_1.jpg"
            ]
        },
        {
            "name": "LocEdu",
            "description": "Trabalho de conclusão de curso na minha graduação em Ciência da Computação, este aplicativo nativo para Android foi construído em Java. O objetivo é listar pontos de interesse no IFSULDEMINAS, Campus Passos, possibilitando o usuário localizar um local e sua própria posição em um mapa virtual.",
            "html_url": "https://github.com/welingtonfidelis/LocEdu",
            "image_url": [
                "https://welingtonfidelisportfolio.s3-sa-east-1.amazonaws.com/repositories/tcc_1.png",
                "https://welingtonfidelisportfolio.s3-sa-east-1.amazonaws.com/repositories/tcc_2.png",
                "https://welingtonfidelisportfolio.s3-sa-east-1.amazonaws.com/repositories/tcc_3.png",
                "https://welingtonfidelisportfolio.s3-sa-east-1.amazonaws.com/repositories/tcc_4.png",
                "https://welingtonfidelisportfolio.s3-sa-east-1.amazonaws.com/repositories/tcc_5.png",
                "https://welingtonfidelisportfolio.s3-sa-east-1.amazonaws.com/repositories/tcc_6.png",
                "https://welingtonfidelisportfolio.s3-sa-east-1.amazonaws.com/repositories/tcc_7.png",
                "https://welingtonfidelisportfolio.s3-sa-east-1.amazonaws.com/repositories/tcc_8.png",
                "https://welingtonfidelisportfolio.s3-sa-east-1.amazonaws.com/repositories/tcc_9.png"
            ]
        },
        {
            "name": "NextLevelWeek_1",
            "description": "Primeira Next Level Week da equipe RocketSeat. Nele foram aplicadas as tecnologias de NodeJs, Reactjs, React Native e Sqlite3 para construção de uma aplicação chamada Ecoleta, que tem objetivo de permitir que empresas responsáveis por coleta de resíduos específicos se cadastrem na plataforma e sejam encontradas e contatadas por usuários através do aplicativo.",
            "html_url": "https://github.com/welingtonfidelis/NextLevelWeek_1",
            "image_url": [
                "https://welingtonfidelisportfolio.s3-sa-east-1.amazonaws.com/repositories/nlw1_1.png",
                "https://welingtonfidelisportfolio.s3-sa-east-1.amazonaws.com/repositories/nlw1_2.png",
                "https://welingtonfidelisportfolio.s3-sa-east-1.amazonaws.com/repositories/nlw1_3.png",
                "https://welingtonfidelisportfolio.s3-sa-east-1.amazonaws.com/repositories/nlw1_4.png",
                "https://welingtonfidelisportfolio.s3-sa-east-1.amazonaws.com/repositories/nlw1_5.png",
                "https://welingtonfidelisportfolio.s3-sa-east-1.amazonaws.com/repositories/nlw1_6.png",
                "https://welingtonfidelisportfolio.s3-sa-east-1.amazonaws.com/repositories/nlw1_7.png",
                "https://welingtonfidelisportfolio.s3-sa-east-1.amazonaws.com/repositories/nlw1_8.png"
            ]
        },
        {
            "name": "portfolio",
            "description": "Portifólio pessoal construído com Next.js e API REST em Node.js",
            "html_url": "https://github.com/welingtonfidelis/portfolio",
            "image_url": [
                "https://welingtonfidelisportfolio.s3-sa-east-1.amazonaws.com/repositories/portfolio_1.png"
            ]
        },
        {
            "name": "ripsta_game",
            "description": "Jogo de plataforma 2D utilizando Javascript (biblioteca p5) construído através da semana de Imersão Game oferecido pelo curso Alura.",
            "html_url": "https://github.com/welingtonfidelis/ripsta_game",
            "image_url": [
                "https://welingtonfidelisportfolio.s3-sa-east-1.amazonaws.com/repositories/Ripsta_game.png"
            ],
            "deploy": "https://welingtonfidelis.github.io/ripsta_game"
        },
        {
            "name": "semana_omnistack_10",
            "description": "Esse projeto é resultado da semana omnistack 10 da equipe RocketSeat. Nele foram aplicadas as tecnologias NodeJs, Reactjs, React Native e MongoDB para construção de uma aplicação que visa oferecer formas de encontrara e compartilhar conhecimento entre desenvoldores através de tecnologias que conheçam.",
            "html_url": "https://github.com/welingtonfidelis/semana_omnistack_10",
            "image_url": [
                "https://welingtonfidelisportfolio.s3-sa-east-1.amazonaws.com/repositories/semana_omnistack_10.png",
                "https://welingtonfidelisportfolio.s3-sa-east-1.amazonaws.com/repositories/semana_omnistack_101.png",
                "https://welingtonfidelisportfolio.s3-sa-east-1.amazonaws.com/repositories/semana_omnistack_102.png"
            ]
        },
        {
            "name": "semana_omnistack_11",
            "description": "Esse projeto é resultado da semana omnistack 11 da equipe RocketSeat. Nele foram aplicadas as tecnologias NodeJs, Reactjs, React Native e Sqlite3 para construção de uma aplicação chamada Be The Hero, que tem objetivo de dar as Ongs uma maneira de compartilhar à população, ocorrências que precisem de auxílio financeiro, para que qualquer pessoa disposta a ajudar com alguma valor possa entrar em contato.",
            "html_url": "https://github.com/welingtonfidelis/semana_omnistack_11",
            "image_url": [
                "https://welingtonfidelisportfolio.s3-sa-east-1.amazonaws.com/repositories/semana_omnistack_11_1.png",
                "https://welingtonfidelisportfolio.s3-sa-east-1.amazonaws.com/repositories/semana_omnistack_11.png",
                "https://welingtonfidelisportfolio.s3-sa-east-1.amazonaws.com/repositories/semana_omnistack_11_2.png",
                "https://welingtonfidelisportfolio.s3-sa-east-1.amazonaws.com/repositories/semana_omnistack_11_3.png",
                "https://welingtonfidelisportfolio.s3-sa-east-1.amazonaws.com/repositories/semana_omnistack_11_4.png"
            ]
        },
        {
            "name": "semana_omnistack_9",
            "description": "Esse projeto é resultado da semana omnistack 9 da equipe RocketSeat. Nele foram aplicadas as tecnologias NodeJs, Reactjs, React Native e MongoDB para construção de uma aplicação que visa oferecer formas de encontrar e compartilhar locais para coworking entre empresas e profissionais.",
            "html_url": "https://github.com/welingtonfidelis/semana_omnistack_9",
            "image_url": [
                "https://welingtonfidelisportfolio.s3-sa-east-1.amazonaws.com/repositories/semana_omnistack_9_1.png",
                "https://welingtonfidelisportfolio.s3-sa-east-1.amazonaws.com/repositories/semana_omnistack_9.png",
                "https://welingtonfidelisportfolio.s3-sa-east-1.amazonaws.com/repositories/semana_omnistack_9_2.png",
                "https://welingtonfidelisportfolio.s3-sa-east-1.amazonaws.com/repositories/semana_omnistack_9_3.png",
                "https://welingtonfidelisportfolio.s3-sa-east-1.amazonaws.com/repositories/semana_omnistack_9_4.png",
                "https://welingtonfidelisportfolio.s3-sa-east-1.amazonaws.com/repositories/semana_omnistack_9_5.png"
            ]
        },
        {
            "name": "utilsApi",
            "description": "Conjunto de métodos/ferramentas genéricas pra uso geral para atender a necessidade de outras APIs ou sistemas/aplicativos web, como disparo de email.",
            "html_url": "https://github.com/welingtonfidelis/utilsApi",
            "image_url": [
                "https://welingtonfidelisportfolio.s3-sa-east-1.amazonaws.com/repositories/api_utils_1.png"
            ]
        }
    ]
}